SlyAPI/__init__.py
SlyAPI/__main__.py
SlyAPI/asyncy.py
SlyAPI/auth.py
SlyAPI/flow.py
SlyAPI/oauth1.py
SlyAPI/oauth2.py
SlyAPI/service_account.py
SlyAPI/web.py
SlyAPI/webapi.py
SlyAPI-0.6.1.dist-info/LICENSE
SlyAPI-0.6.1.dist-info/METADATA
SlyAPI-0.6.1.dist-info/WHEEL
SlyAPI-0.6.1.dist-info/top_level.txt
SlyAPI-0.6.1.dist-info/RECORD
