Metadata-Version: 2.1
Name: SlyAPI
Version: 0.6.1
Summary: No-boilerplate, async and typed web api access with oauth1/2.
Author: Dunkyl 🔣🔣
License: The MIT License
Project-URL: Homepage, https://docs.dunkyl.net/SlyAPI-Python/
Project-URL: Repository, https://github.com/dunkyl/SlyAPI-Python
Project-URL: Documentation, https://docs.dunkyl.net/SlyAPI-Python/
Project-URL: Bug Tracker, https://github.com/dunkyl/SlyAPI-Python/issues
Classifier: Operating System :: OS Independent
Requires-Python: >=3.10
License-File: LICENSE
Requires-Dist: aiohttp>=3.7
Requires-Dist: aiodns>=3.0.0
Requires-Dist: charset-normalizer>=3.0.1
Requires-Dist: pick
Requires-Dist: termcolor
Requires-Dist: PyJWT>=2.9
Requires-Dist: cryptography>=43.0.0
Requires-Dist: typing-extensions
Provides-Extra: dev
Requires-Dist: pytest; extra == "dev"
Requires-Dist: pytest-asyncio; extra == "dev"
Requires-Dist: myst-parser; extra == "dev"
Requires-Dist: furo; extra == "dev"
Requires-Dist: sphinxcontrib-trio; extra == "dev"
Requires-Dist: sphinx-copybutton; extra == "dev"
Requires-Dist: sphinxext-opengraph; extra == "dev"
